asyncfakeyou/__init__.py
asyncfakeyou/asyncfakeyou.py
asyncfakeyou/utils.py
asyncfakeyou-0.1.2.dist-info/LICENSE
asyncfakeyou-0.1.2.dist-info/METADATA
asyncfakeyou-0.1.2.dist-info/WHEEL
asyncfakeyou-0.1.2.dist-info/top_level.txt
asyncfakeyou-0.1.2.dist-info/RECORD
