Metadata-Version: 2.1
Name: asyncfakeyou
Version: 0.1.2
Summary: An asynchronous library for interacting with the FakeYou Text-to-Speech API.
Home-page: https://github.com/NickV1v/AsyncFakeYou
Author: NickV1v
Author-email: vivchar.nikita@yandex.ru
License: MIT
Platform: UNKNOWN
Classifier: Topic :: Multimedia :: Sound/Audio :: Speech
Classifier: Programming Language :: Python :: 3.10
Classifier: Operating System :: OS Independent
Classifier: License :: OSI Approved :: MIT License
Requires-Python: >=3.10
License-File: LICENSE
Requires-Dist: aiohttp (>=3.10.3)
Requires-Dist: aiofiles (>=24.1.0)
Provides-Extra: dev
Requires-Dist: twine (>=5.1.1) ; extra == 'dev'
